simulab/__init__.py
simulab/models/abstract/__init__.py
simulab/models/abstract/agent.py
simulab/models/abstract/model.py
simulab/models/computational/__init__.py
simulab/models/computational/condensation/__init__.py
simulab/models/computational/condensation/model.py
simulab/models/computational/game_of_life/__init__.py
simulab/models/computational/game_of_life/model.py
simulab/models/computational/game_of_life/seeds.py
simulab/models/computational/real_state_market/__init__.py
simulab/models/computational/real_state_market/agent.py
simulab/models/computational/real_state_market/formulas.py
simulab/models/computational/real_state_market/model.py
simulab/models/computational/schelling/__init__.py
simulab/models/computational/schelling/model.py
simulab/simulation/core/__init__.py
simulab/simulation/core/equilibrium_criterion.py
simulab/simulation/core/experiment.py
simulab/simulation/core/lattice.py
simulab/simulation/core/neighborhood.py
simulab/simulation/core/runner.py
simulab/simulation/plotters/__init__.py
simulab/simulation/plotters/animated_lattice.py
simulab/simulation/plotters/categorical_animated_lattice.py
simulab/simulation/plotters/final_grid.py
simulab/simulation/plotters/numerical_series.py
simulab-0.0.18.dist-info/LICENSE
simulab-0.0.18.dist-info/METADATA
simulab-0.0.18.dist-info/WHEEL
simulab-0.0.18.dist-info/RECORD
