Metadata-Version: 2.1
Name: simulab
Version: 0.0.18
Summary: Simple simulation framework, created during a course of the Discrete Events Simulation Laboratory, from the University of Buenos Aires (https://modsimu.exp.dc.uba.ar/sed/)
Home-page: https://github.com/EzequielPuerta/simulab
License: MIT
Author: Armando Ezequiel Puerta
Author-email: armando.ezequiel.puerta@gmail.com
Requires-Python: >=3.10,<4.0
Classifier: Development Status :: 5 - Production/Stable
Classifier: Intended Audience :: Developers
Classifier: License :: OSI Approved :: MIT License
Classifier: Operating System :: OS Independent
Classifier: Programming Language :: Python :: 3
Classifier: Programming Language :: Python :: 3.10
Classifier: Programming Language :: Python :: 3.11
Classifier: Programming Language :: Python :: 3.12
Classifier: Topic :: Software Development
Requires-Dist: networkx (>=3.3,<4.0)
Requires-Dist: numpy (>=1.26.4,<2.0.0)
Requires-Dist: pandas (>=2.2.2,<3.0.0)
Requires-Dist: plotly (>=5.22.0,<6.0.0)
Project-URL: Bug Tracker, https://github.com/EzequielPuerta/simulab/issues
Project-URL: Documentation, https://github.com/EzequielPuerta/simulab
Project-URL: Repository, https://github.com/EzequielPuerta/simulab
